tc3omega/__init__.py
tc3omega/analysis.py
tc3omega/cli.py
tc3omega/constants.py
tc3omega/datareader.py
tc3omega/integrators.cp37-win_amd64.pyd
tc3omega/logmaker.py
tc3omega/example/measured_data_example.csv
tc3omega/example/sample_file_example.txt
tc3omega/example/sample_file_example.yml
tests/__init__.py
tests/test_runexample.py
tc3omega-0.7.dist-info/LICENSE
tc3omega-0.7.dist-info/METADATA
tc3omega-0.7.dist-info/WHEEL
tc3omega-0.7.dist-info/top_level.txt
tc3omega-0.7.dist-info/RECORD
